{
 "mls": "24191711",
 "status": "Active",
 "listingType": "sale",
 "propertyType": "Multi-Family For Sale",
 "price": 699000.0,
 "beds": 4.0,
 "baths": 2.0,
 "sqft": 1616.0,
 "yearBuilt": 1915.0,
 "acres": 0.16,
 "address": {
  "line": "26 Center",
  "city": "Norwalk",
  "state": "Connecticut",
  "zip": "06851"
 },
 "addressWithheld": false,
 "attribution": {
  "office": "Keller Williams Realty",
  "officeId": "KELW130",
  "agent": "Gabby Addison",
  "agentEmail": "gabbyaddison@kw.com",
  "agentPhone": "(203) 438-9494"
 },
 "remarks": "Rare Norwalk opportunity! This first and second floor duplex at 26 Center Ave sits on a tree lined street with convenient sidewalks - offering the perfect house-hack setup: live in one unit and rent the other, or hold both as a turnkey investment. One unit features 1 bedroom (currently being used as 2) and 1 baths across 742 sq ft of well-designed living space, the second unit is upstairs and has 2 bedrooms on one floor and another on the third floor with over 900 sq ft of living area. Solidly built in 1915, this move-in ready property offers solid quality that&apos;s hard to find at this price point. Whether you&apos;re an owner-occupant looking to offset your mortgage or an investor seeking cash flow in one of Fairfield County&apos;s most desirable towns, 26 Center Ave delivers flexibility, privacy, and long-term value on a peaceful street just minutes from shopping, the train station, and all that downtown Norwalk has to offer. Two homes, endless possibilities - don&apos;t miss this one.",
 "photos": [
  "https://smartmls-assets.cdn-connectmls.com/pics/56BC28AFFC642AE7E0631A01100A3008/HD_1784220610161_new_photo.JPEG",
  "https://smartmls-assets.cdn-connectmls.com/pics/56C416FCFA8399C5E063E201100A1DB5/HD_1784248151034_living.JPEG",
  "https://smartmls-assets.cdn-connectmls.com/pics/56C416FCFA8399C5E063E201100A1DB5/HD_1784248148986_entry.JPEG",
  "https://smartmls-assets.cdn-connectmls.com/pics/56C416FCFA8399C5E063E201100A1DB5/HD_1784248150317_kitchen2.JPEG",
  "https://smartmls-assets.cdn-connectmls.com/pics/56C416FCFA8399C5E063E201100A1DB5/HD_1784248149600_kitchen1.JPEG",
  "https://smartmls-assets.cdn-connectmls.com/pics/56C416FCFA8399C5E063E201100A1DB5/HD_1784248151659_pantry.JPEG",
  "https://smartmls-assets.cdn-connectmls.com/pics/56C416FCFA8399C5E063E201100A1DB5/HD_1784248148257_bedroom.JPEG",
  "https://smartmls-assets.cdn-connectmls.com/pics/56C416FCFA8399C5E063E201100A1DB5/HD_1784248147817_bath.JPEG",
  "https://smartmls-assets.cdn-connectmls.com/pics/56C416FCFA8399C5E063E201100A1DB5/HD_1784248505406_bestwasher.JPEG",
  "https://smartmls-assets.cdn-connectmls.com/pics/570EF799B5E8AE96E063E201100AC597/HD_1784574205362_thirdbedroom.JPEG",
  "https://smartmls-assets.cdn-connectmls.com/pics/56C416FCFA8399C5E063E201100A1DB5/HD_1784248677070_best_back.JPEG"
 ],
 "primaryPhotoOnly": false,
 "updated": "2026-07-16T16:56:09",
 "geo": {
  "lat": 41.127915,
  "lng": -73.418258
 },
 "slug": "26-center-norwalk-connecticut-24191711",
 "indexable": true,
 "meta": {
  "disclaimer": "Listing data is provided courtesy of SmartMLS. Information is deemed reliable but not guaranteed accurate by the MLS. IDX information is provided exclusively for consumers' personal, non-commercial use and may not be used for any purpose other than to identify prospective properties consumers may be interested in purchasing.",
  "attribution": "Listing data provided courtesy of SmartMLS."
 }
}