{
 "mls": "24192350",
 "slug": "347-greenwich-avenue-greenwich-connecticut-24192350",
 "status": "Active",
 "listingType": "rent",
 "propertyType": "Residential Rental",
 "price": 3300.0,
 "beds": 3.0,
 "baths": 1.0,
 "sqft": 3572.0,
 "yearBuilt": 1928.0,
 "acres": 0.05,
 "address": {
  "line": "347 Greenwich Avenue",
  "city": "Greenwich",
  "state": "Connecticut",
  "zip": "06830"
 },
 "addressWithheld": false,
 "attribution": {
  "office": "Criterion Real Estate LLC",
  "officeId": "13606",
  "agent": "Daniel Durante",
  "agentEmail": "dan@criterion-re.com",
  "agentPhone": "(203) 998-0799"
 },
 "remarks": "This spacious three-bedroom apartment located on the third floor of a well-maintained building. Nestled in the heart of the Greenwich business district, this residence offers exceptional convenience to shops, restaurants, cafes, and everyday amenities. The train station is just minutes away, making it an excellent option for commuters, while nearby Bruce Park provides access to open green space, walking paths, and recreational facilities. Residents will also enjoy access to two beautiful Greenwich beaches and two town-owned islands, offering a rare combination of in-town living and coastal lifestyle. With easy access to I-95, this location provides both comfort and connectivity in one of Greenwich&apos;s most sought-after areas.",
 "photos": [
  "https://smartmls-assets.cdn-connectmls.com/pics/56CE4F004A1F73D2E063E201100A3179/HD_1784296890358_2E0A8133.JPEG",
  "https://smartmls-assets.cdn-connectmls.com/pics/56CE4F004A1F73D2E063E201100A3179/HD_1784297559403_Greenwich_Ave_Kitchen_Fixed_WB.JPEG",
  "https://smartmls-assets.cdn-connectmls.com/pics/56CE4F004A1F73D2E063E201100A3179/HD_1784296888578_2E0A9012.JPEG",
  "https://smartmls-assets.cdn-connectmls.com/pics/56CE4F004A1F73D2E063E201100A3179/HD_1784296889075_2E0A8972.JPEG",
  "https://smartmls-assets.cdn-connectmls.com/pics/56CE4F004A1F73D2E063E201100A3179/HD_1784296889338_2E0A8962.JPEG",
  "https://smartmls-assets.cdn-connectmls.com/pics/56CE4F004A1F73D2E063E201100A3179/HD_1784296889547_2E0A8977.JPEG",
  "https://smartmls-assets.cdn-connectmls.com/pics/56CE4F004A1F73D2E063E201100A3179/HD_1784296889748_2E0A8987.JPEG",
  "https://smartmls-assets.cdn-connectmls.com/pics/56CE4F004A1F73D2E063E201100A3179/HD_1784296889938_2E0A8997.JPEG",
  "https://smartmls-assets.cdn-connectmls.com/pics/56CE4F004A1F73D2E063E201100A3179/HD_1784296890155_2E0A9002.JPEG",
  "https://smartmls-assets.cdn-connectmls.com/pics/56CE4F004A1F73D2E063E201100A3179/HD_1784296891974_2E0A8967.JPEG",
  "https://smartmls-assets.cdn-connectmls.com/pics/56CE4F004A1F73D2E063E201100A3179/HD_1784296892170_2E0A8992.JPEG",
  "https://smartmls-assets.cdn-connectmls.com/pics/56CE4F004A1F73D2E063E201100A3179/HD_1784296892368_2E0A9007.JPEG"
 ],
 "primaryPhotoOnly": false,
 "updated": "2026-07-20T13:52:42",
 "geo": {
  "lat": 41.024015,
  "lng": -73.624999
 },
 "indexable": true,
 "meta": {
  "disclaimer": "Listing data is provided courtesy of SmartMLS. Information is deemed reliable but not guaranteed accurate by the MLS. IDX information is provided exclusively for consumers' personal, non-commercial use and may not be used for any purpose other than to identify prospective properties consumers may be interested in purchasing.",
  "attribution": "Listing data provided courtesy of SmartMLS."
 }
}