{
 "mls": "24027417",
 "status": "Under Contract",
 "listingType": "sale",
 "propertyType": "Lots and Land For Sale",
 "price": 1625000.0,
 "beds": null,
 "baths": null,
 "sqft": 0.0,
 "yearBuilt": null,
 "acres": 5.56,
 "address": {
  "line": "469L Wilton",
  "city": "New Canaan",
  "state": "Connecticut",
  "zip": "06840"
 },
 "addressWithheld": false,
 "attribution": {
  "office": "Brown Harris Stevens",
  "officeId": "BROWN03",
  "agent": "Mitchell Moore",
  "agentEmail": "mmoore@bhsusa.com",
  "agentPhone": "(203) 966-7800"
 },
 "remarks": "Fantastic level lot with water views and Brook on property. Right of way to Grupes Reservoir LLC.",
 "photos": [
  "https://smartmls-assets.cdn-connectmls.com/pics/1BA08658C456E434E063D501100A968C/HD_1719242649670_003_446339_DJI_20230705143138_0024_D_12624954.JPEG",
  "https://smartmls-assets.cdn-connectmls.com/pics/1BA08658C456E434E063D501100A968C/HD_1719242651283_004_446339_DJI_20230705143451_0027_D_12624955.JPEG",
  "https://smartmls-assets.cdn-connectmls.com/pics/1BA08658C456E434E063D501100A968C/HD_1719242652571_001_446339_DJI_20230705142831_0020_D_12624949.JPEG",
  "https://smartmls-assets.cdn-connectmls.com/pics/1BA08658C456E434E063D501100A968C/HD_1719242654043_002_446339_DJI_20230705143102_0023_D_12624950.JPEG",
  "https://smartmls-assets.cdn-connectmls.com/pics/1BA08658C456E434E063D501100A968C/HD_1719245907163_469_N_Wilton_survey.JPEG"
 ],
 "primaryPhotoOnly": false,
 "updated": "2026-05-28T13:12:09",
 "geo": {
  "lat": 41.19608,
  "lng": -73.49494
 },
 "slug": "469l-wilton-new-canaan-connecticut-24027417",
 "indexable": true,
 "meta": {
  "disclaimer": "Listing data is provided courtesy of SmartMLS. Information is deemed reliable but not guaranteed accurate by the MLS. IDX information is provided exclusively for consumers' personal, non-commercial use and may not be used for any purpose other than to identify prospective properties consumers may be interested in purchasing.",
  "attribution": "Listing data provided courtesy of SmartMLS."
 }
}